supyx/__init__.py
supyx/wxnavimgation/__init__.py
supyx/wxnavimgation/hints.py
supyx/wxnavimgation/keybindings.py
supyx/wxnavimgation/modes.py
supyx/wxnavimgation/navigation.py
supyx/wxnavimgation/search.py
supyx-0.1.0.dist-info/METADATA
supyx-0.1.0.dist-info/WHEEL
supyx-0.1.0.dist-info/licenses/LICENSE
supyx-0.1.0.dist-info/RECORD
