Metadata-Version: 2.4
Name: supyx
Version: 0.1.0
Summary: Personal Python utilities library with vim-like navigation for wxPython
Project-URL: Homepage, https://github.com/SXion/supyx
Project-URL: Repository, https://github.com/SXion/supyx
Project-URL: Issues, https://github.com/SXion/supyx/issues
Author: suxiong
License: MIT
License-File: LICENSE
Keywords: gui,keyboard-navigation,utilities,vim-navigation,wxpython
Classifier: Development Status :: 3 - Alpha
Classifier: Intended Audience :: Developers
Classifier: License :: OSI Approved :: MIT License
Classifier: Programming Language :: Python :: 3
Classifier: Programming Language :: Python :: 3.11
Classifier: Programming Language :: Python :: 3.12
Classifier: Programming Language :: Python :: 3.13
Classifier: Topic :: Software Development :: Libraries :: Python Modules
Classifier: Topic :: Software Development :: User Interfaces
Requires-Python: >=3.11
Provides-Extra: wx
Requires-Dist: wxpython>=4.2.0; extra == 'wx'
